{"C:\\Users\\dell\\Harmony\\source\\Todo\\AppScope\\app.json5":{"hashValue":"6746b2892d1a5cb8cc63921adfc8920e","name":"app.json5","path":"C:\\Users\\dell\\Harmony\\source\\Todo\\AppScope\\app.json5","type":"file","isSymbolicLink":false,"fileMetaData":{"size":211,"lastModifiedTime":1734336015092}},"C:\\Users\\dell\\Harmony\\source\\Todo\\entry\\src\\main\\module.json5":{"hashValue":"f5402a3f4d8ac94b00a347c734903628","name":"module.json5","path":"C:\\Users\\dell\\Harmony\\source\\Todo\\entry\\src\\main\\module.json5","type":"file","isSymbolicLink":false,"fileMetaData":{"size":1342,"lastModifiedTime":1734336015111}},"C:\\Users\\dell\\Harmony\\source\\Todo\\build-profile.json5":{"hashValue":"714cc81f42fe1f2e37f4e354595c8d14","name":"build-profile.json5","path":"C:\\Users\\dell\\Harmony\\source\\Todo\\build-profile.json5","type":"file","isSymbolicLink":false,"fileMetaData":{"size":756,"lastModifiedTime":1734336016954}},"C:\\Users\\dell\\Harmony\\source\\Todo\\entry\\build-profile.json5":{"hashValue":"a39ac6d3fd0be899852208f593e11eff","name":"build-profile.json5","path":"C:\\Users\\dell\\Harmony\\source\\Todo\\entry\\build-profile.json5","type":"file","isSymbolicLink":false,"fileMetaData":{"size":449,"lastModifiedTime":1734336016929}},"C:\\Users\\dell\\Harmony\\source\\Todo\\entry\\src\\main\\resources\\base\\profile\\main_pages.json":{"hashValue":"f75136053dce9b6d47c882c610abc62e","name":"main_pages.json","path":"C:\\Users\\dell\\Harmony\\source\\Todo\\entry\\src\\main\\resources\\base\\profile\\main_pages.json","type":"file","isSymbolicLink":false,"fileMetaData":{"size":78,"lastModifiedTime":1734475091251}},"C:\\Users\\dell\\Harmony\\source\\Todo\\hvigor\\hvigor-config.json5":{"hashValue":"b17a6cb1ae5fd33928b61ad246458bc1","name":"hvigor-config.json5","path":"C:\\Users\\dell\\Harmony\\source\\Todo\\hvigor\\hvigor-config.json5","type":"file","isSymbolicLink":false,"fileMetaData":{"size":1323,"lastModifiedTime":1734336011134}},"C:\\Users\\dell\\Harmony\\source\\Todo\\entry\\src\\mock\\mock-config.json5":{"hashValue":"2b59519ad9d4536cffa2a2fc74577fec","name":"mock-config.json5","path":"C:\\Users\\dell\\Harmony\\source\\Todo\\entry\\src\\mock\\mock-config.json5","type":"file","isSymbolicLink":false,"fileMetaData":{"size":3,"lastModifiedTime":1734336012000}},"C:\\Users\\dell\\Harmony\\source\\Todo\\entry\\oh-package.json5":{"hashValue":"e6a6a9747701ea272f74687c501f1f92","name":"oh-package.json5","path":"C:\\Users\\dell\\Harmony\\source\\Todo\\entry\\oh-package.json5","type":"file","isSymbolicLink":false,"fileMetaData":{"size":183,"lastModifiedTime":1734336011514}},"C:\\Users\\dell\\Harmony\\source\\Todo\\entry\\build\\default\\intermediates\\hap_metadata\\default\\output_metadata.json":{"hashValue":"23594322be8f5209ffea2b2670156edd","name":"output_metadata.json","path":"C:\\Users\\dell\\Harmony\\source\\Todo\\entry\\build\\default\\intermediates\\hap_metadata\\default\\output_metadata.json","type":"file","isSymbolicLink":false,"fileMetaData":{"size":100,"lastModifiedTime":1734336362977}},"C:\\Users\\dell\\Harmony\\source\\Todo\\entry\\build\\default\\intermediates\\merge_profile\\default\\module.json":{"hashValue":"0bee087a5ed918accb8dcf21c8e83162","name":"module.json","path":"C:\\Users\\dell\\Harmony\\source\\Todo\\entry\\build\\default\\intermediates\\merge_profile\\default\\module.json","type":"file","isSymbolicLink":false,"fileMetaData":{"size":1543,"lastModifiedTime":1734336362998}},"C:\\Users\\dell\\Harmony\\source\\Todo\\entry\\build\\default\\generated\\profile\\default\\BuildProfile.ets":{"hashValue":"c75dbcb951a245f4d27ed8db82226088","name":"BuildProfile.ets","path":"C:\\Users\\dell\\Harmony\\source\\Todo\\entry\\build\\default\\generated\\profile\\default\\BuildProfile.ets","type":"file","isSymbolicLink":false,"fileMetaData":{"size":859,"lastModifiedTime":1734336363009}},"C:\\Users\\dell\\Harmony\\source\\Todo\\entry\\build\\default\\intermediates\\loader\\default\\pkgContextInfo.json":{"hashValue":"bbd88a4046952cbedc447156aa47e06e","name":"pkgContextInfo.json","path":"C:\\Users\\dell\\Harmony\\source\\Todo\\entry\\build\\default\\intermediates\\loader\\default\\pkgContextInfo.json","type":"file","isSymbolicLink":false,"fileMetaData":{"size":444,"lastModifiedTime":1734336363063}},"C:\\Users\\dell\\Harmony\\source\\Todo\\entry\\src\\main\\resources\\base\\profile\\backup_config.json":{"hashValue":"173f41df2db9d5c46181454d2e675859","name":"backup_config.json","path":"C:\\Users\\dell\\Harmony\\source\\Todo\\entry\\src\\main\\resources\\base\\profile\\backup_config.json","type":"file","isSymbolicLink":false,"fileMetaData":{"size":36,"lastModifiedTime":1734336012410}},"C:\\Users\\dell\\Harmony\\source\\Todo\\entry\\build\\default\\outputs\\default\\pack.info":{"hashValue":"003f6a8eb1aee7c4b7ccba7bbbd69666","name":"pack.info","path":"C:\\Users\\dell\\Harmony\\source\\Todo\\entry\\build\\default\\outputs\\default\\pack.info","type":"file","isSymbolicLink":false,"fileMetaData":{"size":633,"lastModifiedTime":1734336363103}},"C:\\Users\\dell\\Harmony\\source\\Todo\\entry\\build\\default\\intermediates\\process_profile\\default\\module.json":{"hashValue":"fe77b24e013dd3b29a9e5de97f21a4ad","name":"module.json","path":"C:\\Users\\dell\\Harmony\\source\\Todo\\entry\\build\\default\\intermediates\\process_profile\\default\\module.json","type":"file","isSymbolicLink":false,"fileMetaData":{"size":1629,"lastModifiedTime":1734336364309}},"C:\\Users\\dell\\Harmony\\DevEco\\sdk\\default\\openharmony\\toolchains\\syscap_tool.exe":{"hashValue":"fcd154bad0f4cf1400c329baa7dd9956","name":"syscap_tool.exe","path":"C:\\Users\\dell\\Harmony\\DevEco\\sdk\\default\\openharmony\\toolchains\\syscap_tool.exe","type":"file","isSymbolicLink":false,"fileMetaData":{"size":343552,"lastModifiedTime":1726035590000}},"C:\\Users\\dell\\Harmony\\DevEco\\sdk\\default\\openharmony\\ets\\api\\device-define":{"hashValue":"4001edd39b780f4b6decdc1faf32fa11","name":"device-define","path":"C:\\Users\\dell\\Harmony\\DevEco\\sdk\\default\\openharmony\\ets\\api\\device-define","type":"directory","isSymbolicLink":false,"children":[{"hashValue":"511c4ffcf308ffdf60d4a55d0a67d87f","name":"default.json","path":"C:\\Users\\dell\\Harmony\\DevEco\\sdk\\default\\openharmony\\ets\\api\\device-define\\default.json","type":"file","isSymbolicLink":false,"fileMetaData":{"size":12253,"lastModifiedTime":1726035590000}},{"hashValue":"96d9aa0a396f14129d67ab9c0945b983","name":"liteWearable.json","path":"C:\\Users\\dell\\Harmony\\DevEco\\sdk\\default\\openharmony\\ets\\api\\device-define\\liteWearable.json","type":"file","isSymbolicLink":false,"fileMetaData":{"size":883,"lastModifiedTime":1726035590000}},{"hashValue":"aa2a86f3b5eb87fb5a6056733a5233a6","name":"tablet.json","path":"C:\\Users\\dell\\Harmony\\DevEco\\sdk\\default\\openharmony\\ets\\api\\device-define\\tablet.json","type":"file","isSymbolicLink":false,"fileMetaData":{"size":11820,"lastModifiedTime":1726035590000}}]},"C:\\Users\\dell\\Harmony\\source\\Todo\\oh-package.json5":{"hashValue":"33fc7bfb467ddda1d3551acd56b58933","name":"oh-package.json5","path":"C:\\Users\\dell\\Harmony\\source\\Todo\\oh-package.json5","type":"file","isSymbolicLink":false,"fileMetaData":{"size":210,"lastModifiedTime":1734336016965}},"C:\\Users\\dell\\Harmony\\source\\Todo\\entry\\build\\default\\intermediates\\router_map\\default\\temp-router-map.json":{"hashValue":"cae0b18b39ff07033126af4b6486d2c2","name":"temp-router-map.json","path":"C:\\Users\\dell\\Harmony\\source\\Todo\\entry\\build\\default\\intermediates\\router_map\\default\\temp-router-map.json","type":"file","isSymbolicLink":false,"fileMetaData":{"size":16,"lastModifiedTime":1734336364339}},"C:\\Users\\dell\\Harmony\\source\\Todo\\entry\\build\\default\\intermediates\\router_map\\default\\loader-router-map.json":{"hashValue":"34fbb8ad860751ba294b1d921add8bcd","name":"loader-router-map.json","path":"C:\\Users\\dell\\Harmony\\source\\Todo\\entry\\build\\default\\intermediates\\router_map\\default\\loader-router-map.json","type":"file","isSymbolicLink":false,"fileMetaData":{"size":16,"lastModifiedTime":1734336364341}},"C:\\Users\\dell\\Harmony\\source\\Todo\\entry\\build\\default\\intermediates\\res\\default\\resConfig.json":{"hashValue":"99394e6b6a1e34f82dadf252006606fa","name":"resConfig.json","path":"C:\\Users\\dell\\Harmony\\source\\Todo\\entry\\build\\default\\intermediates\\res\\default\\resConfig.json","type":"file","isSymbolicLink":false,"fileMetaData":{"size":960,"lastModifiedTime":1734336364396}},"C:\\Users\\dell\\Harmony\\source\\Todo\\entry\\build\\default\\intermediates\\loader\\default\\loader.json":{"hashValue":"b3b4bb6ec5d051424636cfe8833b09aa","name":"loader.json","path":"C:\\Users\\dell\\Harmony\\source\\Todo\\entry\\build\\default\\intermediates\\loader\\default\\loader.json","type":"file","isSymbolicLink":false,"fileMetaData":{"size":919,"lastModifiedTime":1734336364453}},"C:\\Users\\dell\\Harmony\\source\\Todo\\entry\\build\\default\\intermediates\\libs\\default":{"hashValue":"","name":"default","path":"C:\\Users\\dell\\Harmony\\source\\Todo\\entry\\build\\default\\intermediates\\libs\\default","type":"directory","isSymbolicLink":false,"children":[]},"C:\\Users\\dell\\Harmony\\source\\Todo\\entry\\src\\main\\resources":{"hashValue":"76d0c5f17d491bceeee14737bf9ab34a","name":"resources","path":"C:\\Users\\dell\\Harmony\\source\\Todo\\entry\\src\\main\\resources","type":"directory","isSymbolicLink":false,"children":[{"hashValue":"3d0c191abe22856cd75971aae2907b3b","name":"base","path":"C:\\Users\\dell\\Harmony\\source\\Todo\\entry\\src\\main\\resources\\base","type":"directory","isSymbolicLink":false,"children":[{"hashValue":"e138055cf2393a524b035ea8257f5ec9","name":"element","path":"C:\\Users\\dell\\Harmony\\source\\Todo\\entry\\src\\main\\resources\\base\\element","type":"directory","isSymbolicLink":false,"children":[{"hashValue":"293e3b1f79b1f549aa2b49c1c04da926","name":"color.json","path":"C:\\Users\\dell\\Harmony\\source\\Todo\\entry\\src\\main\\resources\\base\\element\\color.json","type":"file","isSymbolicLink":false,"fileMetaData":{"size":105,"lastModifiedTime":1734336012126}},{"hashValue":"88a96a2a9fe36016295c6c10934b001f","name":"string.json","path":"C:\\Users\\dell\\Harmony\\source\\Todo\\entry\\src\\main\\resources\\base\\element\\string.json","type":"file","isSymbolicLink":false,"fileMetaData":{"size":247,"lastModifiedTime":1734336016897}}]},{"hashValue":"2ba481394f7de1508e2dab4e79cd9224","name":"media","path":"C:\\Users\\dell\\Harmony\\source\\Todo\\entry\\src\\main\\resources\\base\\media","type":"directory","isSymbolicLink":false,"children":[{"hashValue":"bb91c5f0bed2c3410805d9615e42a859","name":"background.png","path":"C:\\Users\\dell\\Harmony\\source\\Todo\\entry\\src\\main\\resources\\base\\media\\background.png","type":"file","isSymbolicLink":false,"fileMetaData":{"size":57364,"lastModifiedTime":1734336012155}},{"hashValue":"af351455765061b623e111f1a8d87591","name":"foreground.png","path":"C:\\Users\\dell\\Harmony\\source\\Todo\\entry\\src\\main\\resources\\base\\media\\foreground.png","type":"file","isSymbolicLink":false,"fileMetaData":{"size":12430,"lastModifiedTime":1734336012179}},{"hashValue":"c1d61c56d0371da9bc166c578a5aca0d","name":"layered_image.json","path":"C:\\Users\\dell\\Harmony\\source\\Todo\\entry\\src\\main\\resources\\base\\media\\layered_image.json","type":"file","isSymbolicLink":false,"fileMetaData":{"size":109,"lastModifiedTime":1734336012199}},{"hashValue":"07492a19b1a97de1f1ed179ce76348e5","name":"startIcon.png","path":"C:\\Users\\dell\\Harmony\\source\\Todo\\entry\\src\\main\\resources\\base\\media\\startIcon.png","type":"file","isSymbolicLink":false,"fileMetaData":{"size":20093,"lastModifiedTime":1734336012233}}]},{"hashValue":"9907b8f5c3879467b62b074b46d642b4","name":"profile","path":"C:\\Users\\dell\\Harmony\\source\\Todo\\entry\\src\\main\\resources\\base\\profile","type":"directory","isSymbolicLink":false,"children":[{"hashValue":"173f41df2db9d5c46181454d2e675859","name":"backup_config.json","path":"C:\\Users\\dell\\Harmony\\source\\Todo\\entry\\src\\main\\resources\\base\\profile\\backup_config.json","type":"file","isSymbolicLink":false,"fileMetaData":{"size":36,"lastModifiedTime":1734336012410}},{"hashValue":"f75136053dce9b6d47c882c610abc62e","name":"main_pages.json","path":"C:\\Users\\dell\\Harmony\\source\\Todo\\entry\\src\\main\\resources\\base\\profile\\main_pages.json","type":"file","isSymbolicLink":false,"fileMetaData":{"size":78,"lastModifiedTime":1734475091251}}]}]},{"hashValue":"9c0968eab3a09cde64fe123b72e9e792","name":"en_US","path":"C:\\Users\\dell\\Harmony\\source\\Todo\\entry\\src\\main\\resources\\en_US","type":"directory","isSymbolicLink":false,"children":[{"hashValue":"6da7c34989341b75e5b8c85b152008c6","name":"element","path":"C:\\Users\\dell\\Harmony\\source\\Todo\\entry\\src\\main\\resources\\en_US\\element","type":"directory","isSymbolicLink":false,"children":[{"hashValue":"a734cba6b678151843df28abdb434340","name":"string.json","path":"C:\\Users\\dell\\Harmony\\source\\Todo\\entry\\src\\main\\resources\\en_US\\element\\string.json","type":"file","isSymbolicLink":false,"fileMetaData":{"size":247,"lastModifiedTime":1734336016980}}]}]},{"hashValue":"","name":"rawfile","path":"C:\\Users\\dell\\Harmony\\source\\Todo\\entry\\src\\main\\resources\\rawfile","type":"directory","isSymbolicLink":false,"children":[]},{"hashValue":"19e4160fbb0b4c86592ffe8ff7d93df2","name":"zh_CN","path":"C:\\Users\\dell\\Harmony\\source\\Todo\\entry\\src\\main\\resources\\zh_CN","type":"directory","isSymbolicLink":false,"children":[{"hashValue":"3e09257ee0aef550f724699e877947f6","name":"element","path":"C:\\Users\\dell\\Harmony\\source\\Todo\\entry\\src\\main\\resources\\zh_CN\\element","type":"directory","isSymbolicLink":false,"children":[{"hashValue":"d3052fa063cc22b9cc4b1d8057858e07","name":"string.json","path":"C:\\Users\\dell\\Harmony\\source\\Todo\\entry\\src\\main\\resources\\zh_CN\\element\\string.json","type":"file","isSymbolicLink":false,"fileMetaData":{"size":241,"lastModifiedTime":1734336016915}}]}]}]},"C:\\Users\\dell\\Harmony\\source\\Todo\\AppScope\\resources":{"hashValue":"610f54c462a191c3dcfe839a61a54f09","name":"resources","path":"C:\\Users\\dell\\Harmony\\source\\Todo\\AppScope\\resources","type":"directory","isSymbolicLink":false,"children":[{"hashValue":"e31a19305c84a0d8906e490eb510dffd","name":"base","path":"C:\\Users\\dell\\Harmony\\source\\Todo\\AppScope\\resources\\base","type":"directory","isSymbolicLink":false,"children":[{"hashValue":"26ef234c13db6df2412d1e08602e8425","name":"element","path":"C:\\Users\\dell\\Harmony\\source\\Todo\\AppScope\\resources\\base\\element","type":"directory","isSymbolicLink":false,"children":[{"hashValue":"36bbd941814f400941f288c635dde37e","name":"string.json","path":"C:\\Users\\dell\\Harmony\\source\\Todo\\AppScope\\resources\\base\\element\\string.json","type":"file","isSymbolicLink":false,"fileMetaData":{"size":190,"lastModifiedTime":1734353976108}}]},{"hashValue":"6be8f727a4221726637b76a4a1a479d3","name":"media","path":"C:\\Users\\dell\\Harmony\\source\\Todo\\AppScope\\resources\\base\\media","type":"directory","isSymbolicLink":false,"children":[{"hashValue":"7db85e060de1f9bd98471b2c999c95d4","name":"app_icon.png","path":"C:\\Users\\dell\\Harmony\\source\\Todo\\AppScope\\resources\\base\\media\\app_icon.png","type":"file","isSymbolicLink":false,"fileMetaData":{"size":2777,"lastModifiedTime":1734336011208}}]}]}]},"C:\\Users\\dell\\Harmony\\source\\Todo\\entry\\build\\default\\intermediates\\res\\default":{"hashValue":"5ddb55eef65b0e5911b198e0acaf32df","name":"default","path":"C:\\Users\\dell\\Harmony\\source\\Todo\\entry\\build\\default\\intermediates\\res\\default","type":"directory","isSymbolicLink":false,"children":[{"hashValue":"11079679afbcf83437dd25e985cee7e4","name":"ids_map","path":"C:\\Users\\dell\\Harmony\\source\\Todo\\entry\\build\\default\\intermediates\\res\\default\\ids_map","type":"directory","isSymbolicLink":false,"children":[{"hashValue":"8fee2fe95e49e8cf6302e757e3717f51","name":"id_defined.json","path":"C:\\Users\\dell\\Harmony\\source\\Todo\\entry\\build\\default\\intermediates\\res\\default\\ids_map\\id_defined.json","type":"file","isSymbolicLink":false,"fileMetaData":{"size":1023,"lastModifiedTime":1734526711359}}]},{"hashValue":"acb42440268fd843a60b800e2a6cf8e1","name":"module.json","path":"C:\\Users\\dell\\Harmony\\source\\Todo\\entry\\build\\default\\intermediates\\res\\default\\module.json","type":"file","isSymbolicLink":false,"fileMetaData":{"size":1809,"lastModifiedTime":1734526711355}},{"hashValue":"99394e6b6a1e34f82dadf252006606fa","name":"resConfig.json","path":"C:\\Users\\dell\\Harmony\\source\\Todo\\entry\\build\\default\\intermediates\\res\\default\\resConfig.json","type":"file","isSymbolicLink":false,"fileMetaData":{"size":960,"lastModifiedTime":1734336364396}},{"hashValue":"663fa75ea16872e384c126b0beb9004c","name":"resources","path":"C:\\Users\\dell\\Harmony\\source\\Todo\\entry\\build\\default\\intermediates\\res\\default\\resources","type":"directory","isSymbolicLink":false,"children":[{"hashValue":"af86336f0d00df0033504b9c2f662921","name":"base","path":"C:\\Users\\dell\\Harmony\\source\\Todo\\entry\\build\\default\\intermediates\\res\\default\\resources\\base","type":"directory","isSymbolicLink":false,"children":[{"hashValue":"4de9eaefe648496291e2bd0307a7a670","name":"media","path":"C:\\Users\\dell\\Harmony\\source\\Todo\\entry\\build\\default\\intermediates\\res\\default\\resources\\base\\media","type":"directory","isSymbolicLink":false,"children":[{"hashValue":"7db85e060de1f9bd98471b2c999c95d4","name":"app_icon.png","path":"C:\\Users\\dell\\Harmony\\source\\Todo\\entry\\build\\default\\intermediates\\res\\default\\resources\\base\\media\\app_icon.png","type":"file","isSymbolicLink":false,"fileMetaData":{"size":2777,"lastModifiedTime":1734336011208}},{"hashValue":"bb91c5f0bed2c3410805d9615e42a859","name":"background.png","path":"C:\\Users\\dell\\Harmony\\source\\Todo\\entry\\build\\default\\intermediates\\res\\default\\resources\\base\\media\\background.png","type":"file","isSymbolicLink":false,"fileMetaData":{"size":57364,"lastModifiedTime":1734336012155}},{"hashValue":"af351455765061b623e111f1a8d87591","name":"foreground.png","path":"C:\\Users\\dell\\Harmony\\source\\Todo\\entry\\build\\default\\intermediates\\res\\default\\resources\\base\\media\\foreground.png","type":"file","isSymbolicLink":false,"fileMetaData":{"size":12430,"lastModifiedTime":1734336012179}},{"hashValue":"502547eeda21864ac8170cd7850d1d70","name":"layered_image.json","path":"C:\\Users\\dell\\Harmony\\source\\Todo\\entry\\build\\default\\intermediates\\res\\default\\resources\\base\\media\\layered_image.json","type":"file","isSymbolicLink":false,"fileMetaData":{"size":95,"lastModifiedTime":1734526711350}},{"hashValue":"07492a19b1a97de1f1ed179ce76348e5","name":"startIcon.png","path":"C:\\Users\\dell\\Harmony\\source\\Todo\\entry\\build\\default\\intermediates\\res\\default\\resources\\base\\media\\startIcon.png","type":"file","isSymbolicLink":false,"fileMetaData":{"size":20093,"lastModifiedTime":1734336012233}}]},{"hashValue":"9907b8f5c3879467b62b074b46d642b4","name":"profile","path":"C:\\Users\\dell\\Harmony\\source\\Todo\\entry\\build\\default\\intermediates\\res\\default\\resources\\base\\profile","type":"directory","isSymbolicLink":false,"children":[{"hashValue":"173f41df2db9d5c46181454d2e675859","name":"backup_config.json","path":"C:\\Users\\dell\\Harmony\\source\\Todo\\entry\\build\\default\\intermediates\\res\\default\\resources\\base\\profile\\backup_config.json","type":"file","isSymbolicLink":false,"fileMetaData":{"size":36,"lastModifiedTime":1734336012410}},{"hashValue":"f75136053dce9b6d47c882c610abc62e","name":"main_pages.json","path":"C:\\Users\\dell\\Harmony\\source\\Todo\\entry\\build\\default\\intermediates\\res\\default\\resources\\base\\profile\\main_pages.json","type":"file","isSymbolicLink":false,"fileMetaData":{"size":78,"lastModifiedTime":1734475091251}}]}]},{"hashValue":"","name":"rawfile","path":"C:\\Users\\dell\\Harmony\\source\\Todo\\entry\\build\\default\\intermediates\\res\\default\\resources\\rawfile","type":"directory","isSymbolicLink":false,"children":[]}]},{"hashValue":"40c95718ea48821feef076c9ce62350d","name":"resources.index","path":"C:\\Users\\dell\\Harmony\\source\\Todo\\entry\\build\\default\\intermediates\\res\\default\\resources.index","type":"file","isSymbolicLink":false,"fileMetaData":{"size":1415,"lastModifiedTime":1734526711358}},{"hashValue":"ebc2a9d17cc53553b2b3af9abd375d84","name":"ResourceTable.txt","path":"C:\\Users\\dell\\Harmony\\source\\Todo\\entry\\build\\default\\intermediates\\res\\default\\ResourceTable.txt","type":"file","isSymbolicLink":false,"fileMetaData":{"size":409,"lastModifiedTime":1734526711352}}]},"C:\\Users\\dell\\Harmony\\source\\Todo\\entry\\build\\default\\generated\\r\\default\\ResourceTable.h":{"hashValue":"8a2e547824479c998e02160466d0011a","name":"ResourceTable.h","path":"C:\\Users\\dell\\Harmony\\source\\Todo\\entry\\build\\default\\generated\\r\\default\\ResourceTable.h","type":"file","isSymbolicLink":false,"fileMetaData":{"size":1336,"lastModifiedTime":1734526711351}},"C:\\Users\\dell\\Harmony\\source\\Todo\\entry\\build\\default\\generated\\r\\default":{"hashValue":"807c8a01b722c8b68ea3d3084716809f","name":"default","path":"C:\\Users\\dell\\Harmony\\source\\Todo\\entry\\build\\default\\generated\\r\\default","type":"directory","isSymbolicLink":false,"children":[{"hashValue":"8a2e547824479c998e02160466d0011a","name":"ResourceTable.h","path":"C:\\Users\\dell\\Harmony\\source\\Todo\\entry\\build\\default\\generated\\r\\default\\ResourceTable.h","type":"file","isSymbolicLink":false,"fileMetaData":{"size":1336,"lastModifiedTime":1734526711351}}]},"C:\\Users\\dell\\Harmony\\source\\Todo\\entry\\build\\default\\intermediates\\loader\\default":{"hashValue":"f5ccae4e50709b4589f5d0f9a8409320","name":"default","path":"C:\\Users\\dell\\Harmony\\source\\Todo\\entry\\build\\default\\intermediates\\loader\\default","type":"directory","isSymbolicLink":false,"children":[{"hashValue":"b3b4bb6ec5d051424636cfe8833b09aa","name":"loader.json","path":"C:\\Users\\dell\\Harmony\\source\\Todo\\entry\\build\\default\\intermediates\\loader\\default\\loader.json","type":"file","isSymbolicLink":false,"fileMetaData":{"size":919,"lastModifiedTime":1734336364453}},{"hashValue":"bbd88a4046952cbedc447156aa47e06e","name":"pkgContextInfo.json","path":"C:\\Users\\dell\\Harmony\\source\\Todo\\entry\\build\\default\\intermediates\\loader\\default\\pkgContextInfo.json","type":"file","isSymbolicLink":false,"fileMetaData":{"size":444,"lastModifiedTime":1734336363063}}]},"C:\\Users\\dell\\Harmony\\source\\Todo\\entry\\build\\default\\intermediates\\res\\default\\resources\\rawfile":{"hashValue":"","name":"rawfile","path":"C:\\Users\\dell\\Harmony\\source\\Todo\\entry\\build\\default\\intermediates\\res\\default\\resources\\rawfile","type":"directory","isSymbolicLink":false,"children":[]},"C:\\Users\\dell\\Harmony\\source\\Todo\\entry\\build\\default\\intermediates\\res\\default\\ResourceTable.txt":{"hashValue":"ebc2a9d17cc53553b2b3af9abd375d84","name":"ResourceTable.txt","path":"C:\\Users\\dell\\Harmony\\source\\Todo\\entry\\build\\default\\intermediates\\res\\default\\ResourceTable.txt","type":"file","isSymbolicLink":false,"fileMetaData":{"size":409,"lastModifiedTime":1734526711352}},"C:\\Users\\dell\\Harmony\\source\\Todo\\entry\\build\\default\\intermediates\\res\\default\\module.json":{"hashValue":"acb42440268fd843a60b800e2a6cf8e1","name":"module.json","path":"C:\\Users\\dell\\Harmony\\source\\Todo\\entry\\build\\default\\intermediates\\res\\default\\module.json","type":"file","isSymbolicLink":false,"fileMetaData":{"size":1809,"lastModifiedTime":1734526711355}},"C:\\Users\\dell\\Harmony\\source\\Todo\\entry\\build\\default\\intermediates\\res\\default\\resources\\base\\profile":{"hashValue":"9907b8f5c3879467b62b074b46d642b4","name":"profile","path":"C:\\Users\\dell\\Harmony\\source\\Todo\\entry\\build\\default\\intermediates\\res\\default\\resources\\base\\profile","type":"directory","isSymbolicLink":false,"children":[{"hashValue":"173f41df2db9d5c46181454d2e675859","name":"backup_config.json","path":"C:\\Users\\dell\\Harmony\\source\\Todo\\entry\\build\\default\\intermediates\\res\\default\\resources\\base\\profile\\backup_config.json","type":"file","isSymbolicLink":false,"fileMetaData":{"size":36,"lastModifiedTime":1734336012410}},{"hashValue":"f75136053dce9b6d47c882c610abc62e","name":"main_pages.json","path":"C:\\Users\\dell\\Harmony\\source\\Todo\\entry\\build\\default\\intermediates\\res\\default\\resources\\base\\profile\\main_pages.json","type":"file","isSymbolicLink":false,"fileMetaData":{"size":78,"lastModifiedTime":1734475091251}}]},"C:\\Users\\dell\\Harmony\\source\\Todo\\entry\\src\\main\\ets":{"hashValue":"0aa42991414f689dddce4bf1c481ab10","name":"ets","path":"C:\\Users\\dell\\Harmony\\source\\Todo\\entry\\src\\main\\ets","type":"directory","isSymbolicLink":false,"children":[{"hashValue":"0d6c97e2fa0024aae88e1ff8f600320b","name":"common","path":"C:\\Users\\dell\\Harmony\\source\\Todo\\entry\\src\\main\\ets\\common","type":"directory","isSymbolicLink":false,"children":[{"hashValue":"232795537de679918b2acbac2e4ef444","name":"constants","path":"C:\\Users\\dell\\Harmony\\source\\Todo\\entry\\src\\main\\ets\\common\\constants","type":"directory","isSymbolicLink":false,"children":[{"hashValue":"1c7849ce83de52aa8e70cdc5d35838c8","name":"CommonConstants.ets","path":"C:\\Users\\dell\\Harmony\\source\\Todo\\entry\\src\\main\\ets\\common\\constants\\CommonConstants.ets","type":"file","isSymbolicLink":false,"fileMetaData":{"size":2787,"lastModifiedTime":1734570139014}}]},{"hashValue":"6ef08665eb53c4b75206b8eb398b1511","name":"database","path":"C:\\Users\\dell\\Harmony\\source\\Todo\\entry\\src\\main\\ets\\common\\database","type":"directory","isSymbolicLink":false,"children":[{"hashValue":"e5cfd096935d478e357d949b7d0e0965","name":"Rdb.ets","path":"C:\\Users\\dell\\Harmony\\source\\Todo\\entry\\src\\main\\ets\\common\\database\\Rdb.ets","type":"file","isSymbolicLink":false,"fileMetaData":{"size":4908,"lastModifiedTime":1722649938000}},{"hashValue":"14f437fec24ea49c2af1c7b938e7d0a6","name":"tables","path":"C:\\Users\\dell\\Harmony\\source\\Todo\\entry\\src\\main\\ets\\common\\database\\tables","type":"directory","isSymbolicLink":false,"children":[{"hashValue":"70bb75cb2e304691a04ca36cb5413223","name":"TaskTable.ets","path":"C:\\Users\\dell\\Harmony\\source\\Todo\\entry\\src\\main\\ets\\common\\database\\tables\\TaskTable.ets","type":"file","isSymbolicLink":false,"fileMetaData":{"size":3986,"lastModifiedTime":1734569703813}},{"hashValue":"6604a30d76b992f55b2b5f96edaed466","name":"UserTable.ets","path":"C:\\Users\\dell\\Harmony\\source\\Todo\\entry\\src\\main\\ets\\common\\database\\tables\\UserTable.ets","type":"file","isSymbolicLink":false,"fileMetaData":{"size":3451,"lastModifiedTime":1734549757737}}]}]},{"hashValue":"553d52f579920b5ac75689568a2e2a09","name":"utils","path":"C:\\Users\\dell\\Harmony\\source\\Todo\\entry\\src\\main\\ets\\common\\utils","type":"directory","isSymbolicLink":false,"children":[{"hashValue":"a6209034d46b44ed947ef33e8d0aa234","name":"Logger.ets","path":"C:\\Users\\dell\\Harmony\\source\\Todo\\entry\\src\\main\\ets\\common\\utils\\Logger.ets","type":"file","isSymbolicLink":false,"fileMetaData":{"size":1598,"lastModifiedTime":1722649938000}}]}]},{"hashValue":"59046182a970cecf2450e7fad064637a","name":"database","path":"C:\\Users\\dell\\Harmony\\source\\Todo\\entry\\src\\main\\ets\\database","type":"directory","isSymbolicLink":false,"children":[{"hashValue":"916eed49c7ca60d73e61acf19946a704","name":"Rdb.ets","path":"C:\\Users\\dell\\Harmony\\source\\Todo\\entry\\src\\main\\ets\\database\\Rdb.ets","type":"file","isSymbolicLink":false,"fileMetaData":{"size":6416,"lastModifiedTime":1734474864574}}]},{"hashValue":"55925e9832707531f75653b4dd7b8525","name":"entryability","path":"C:\\Users\\dell\\Harmony\\source\\Todo\\entry\\src\\main\\ets\\entryability","type":"directory","isSymbolicLink":false,"children":[{"hashValue":"7a7feeb7f9ff79ae96933e2e9fb0a64f","name":"EntryAbility.ets","path":"C:\\Users\\dell\\Harmony\\source\\Todo\\entry\\src\\main\\ets\\entryability\\EntryAbility.ets","type":"file","isSymbolicLink":false,"fileMetaData":{"size":1474,"lastModifiedTime":1734526687407}}]},{"hashValue":"cc942674c0f149e7d2d7a0aab3ad1b4b","name":"entrybackupability","path":"C:\\Users\\dell\\Harmony\\source\\Todo\\entry\\src\\main\\ets\\entrybackupability","type":"directory","isSymbolicLink":false,"children":[{"hashValue":"755ff26944a508bdbfd60c6717494883","name":"EntryBackupAbility.ets","path":"C:\\Users\\dell\\Harmony\\source\\Todo\\entry\\src\\main\\ets\\entrybackupability\\EntryBackupAbility.ets","type":"file","isSymbolicLink":false,"fileMetaData":{"size":436,"lastModifiedTime":1734336016942}}]},{"hashValue":"7c448ecc62d823e44895eef92b249b77","name":"pages","path":"C:\\Users\\dell\\Harmony\\source\\Todo\\entry\\src\\main\\ets\\pages","type":"directory","isSymbolicLink":false,"children":[{"hashValue":"c57f65b6df4d386d5c71f13af88bb2da","name":"CountDown.ets","path":"C:\\Users\\dell\\Harmony\\source\\Todo\\entry\\src\\main\\ets\\pages\\CountDown.ets","type":"file","isSymbolicLink":false,"fileMetaData":{"size":23088,"lastModifiedTime":1734569635507}},{"hashValue":"aeefcfbd7f0a733769499bc23a57d6e2","name":"Index.ets","path":"C:\\Users\\dell\\Harmony\\source\\Todo\\entry\\src\\main\\ets\\pages\\Index.ets","type":"file","isSymbolicLink":false,"fileMetaData":{"size":9234,"lastModifiedTime":1734569627343}},{"hashValue":"5a897ade93ff93d086211b667fabfebe","name":"Login.ets","path":"C:\\Users\\dell\\Harmony\\source\\Todo\\entry\\src\\main\\ets\\pages\\Login.ets","type":"file","isSymbolicLink":false,"fileMetaData":{"size":4174,"lastModifiedTime":1734570327963}}]},{"hashValue":"ffbf6b826b00e3af1aaa9bf7ec807b47","name":"view","path":"C:\\Users\\dell\\Harmony\\source\\Todo\\entry\\src\\main\\ets\\view","type":"directory","isSymbolicLink":false,"children":[{"hashValue":"56a642d3f4cea2275cd8c64ae3366278","name":"DialogComponent.ets","path":"C:\\Users\\dell\\Harmony\\source\\Todo\\entry\\src\\main\\ets\\view\\DialogComponent.ets","type":"file","isSymbolicLink":false,"fileMetaData":{"size":2783,"lastModifiedTime":1734569799519}}]},{"hashValue":"1791fa543485ad30cf1a4f7c0a770390","name":"viewmodel","path":"C:\\Users\\dell\\Harmony\\source\\Todo\\entry\\src\\main\\ets\\viewmodel","type":"directory","isSymbolicLink":false,"children":[{"hashValue":"04d5c900d77350fb978ace2243eb6caf","name":"ConstantsInterface.ets","path":"C:\\Users\\dell\\Harmony\\source\\Todo\\entry\\src\\main\\ets\\viewmodel\\ConstantsInterface.ets","type":"file","isSymbolicLink":false,"fileMetaData":{"size":817,"lastModifiedTime":1734533232141}},{"hashValue":"c66ae160ee1885bdb661638dcabd9f92","name":"TaskData.ets","path":"C:\\Users\\dell\\Harmony\\source\\Todo\\entry\\src\\main\\ets\\viewmodel\\TaskData.ets","type":"file","isSymbolicLink":false,"fileMetaData":{"size":822,"lastModifiedTime":1734569717352}},{"hashValue":"72a721f81865181545717cc38b99fc3a","name":"UserData.ets","path":"C:\\Users\\dell\\Harmony\\source\\Todo\\entry\\src\\main\\ets\\viewmodel\\UserData.ets","type":"file","isSymbolicLink":false,"fileMetaData":{"size":726,"lastModifiedTime":1734532725344}}]}]},"C:\\Users\\dell\\Harmony\\source\\Todo\\entry\\build\\default\\intermediates\\loader_out\\default\\ets":{"hashValue":"c1d98b5caa75ab2e8f9bd5c3e412f54d","name":"ets","path":"C:\\Users\\dell\\Harmony\\source\\Todo\\entry\\build\\default\\intermediates\\loader_out\\default\\ets","type":"directory","isSymbolicLink":false,"children":[{"hashValue":"0a5bd40118a6b9d4fdd62314cc8dbb87","name":"modules.abc","path":"C:\\Users\\dell\\Harmony\\source\\Todo\\entry\\build\\default\\intermediates\\loader_out\\default\\ets\\modules.abc","type":"file","isSymbolicLink":false,"fileMetaData":{"size":111536,"lastModifiedTime":1734570332455}},{"hashValue":"fefd7dc4ecc25b61518131b3a7eae388","name":"sourceMaps.map","path":"C:\\Users\\dell\\Harmony\\source\\Todo\\entry\\build\\default\\intermediates\\loader_out\\default\\ets\\sourceMaps.map","type":"file","isSymbolicLink":false,"fileMetaData":{"size":42000,"lastModifiedTime":1734570331833}}]},"C:\\Users\\dell\\Harmony\\source\\Todo\\entry\\build\\default\\intermediates\\stripped_native_libs\\default":{"hashValue":"","name":"default","path":"C:\\Users\\dell\\Harmony\\source\\Todo\\entry\\build\\default\\intermediates\\stripped_native_libs\\default","type":"directory","isSymbolicLink":false,"children":[]},"C:\\Users\\dell\\Harmony\\source\\Todo\\entry\\build\\default\\intermediates\\patch\\default\\base_native_libs.json":{"hashValue":"922ba4a4f0e3cee9682c2f69dad4bfdd","name":"base_native_libs.json","path":"C:\\Users\\dell\\Harmony\\source\\Todo\\entry\\build\\default\\intermediates\\patch\\default\\base_native_libs.json","type":"file","isSymbolicLink":false,"fileMetaData":{"size":25,"lastModifiedTime":1734336369191}},"C:\\Users\\dell\\Harmony\\source\\Todo\\entry\\build\\default\\intermediates\\package\\default\\module.json":{"hashValue":"acb42440268fd843a60b800e2a6cf8e1","name":"module.json","path":"C:\\Users\\dell\\Harmony\\source\\Todo\\entry\\build\\default\\intermediates\\package\\default\\module.json","type":"file","isSymbolicLink":false,"fileMetaData":{"size":1809,"lastModifiedTime":1734526711355}},"C:\\Users\\dell\\Harmony\\source\\Todo\\entry\\build\\default\\intermediates\\res\\default\\resources":{"hashValue":"663fa75ea16872e384c126b0beb9004c","name":"resources","path":"C:\\Users\\dell\\Harmony\\source\\Todo\\entry\\build\\default\\intermediates\\res\\default\\resources","type":"directory","isSymbolicLink":false,"children":[{"hashValue":"af86336f0d00df0033504b9c2f662921","name":"base","path":"C:\\Users\\dell\\Harmony\\source\\Todo\\entry\\build\\default\\intermediates\\res\\default\\resources\\base","type":"directory","isSymbolicLink":false,"children":[{"hashValue":"4de9eaefe648496291e2bd0307a7a670","name":"media","path":"C:\\Users\\dell\\Harmony\\source\\Todo\\entry\\build\\default\\intermediates\\res\\default\\resources\\base\\media","type":"directory","isSymbolicLink":false,"children":[{"hashValue":"7db85e060de1f9bd98471b2c999c95d4","name":"app_icon.png","path":"C:\\Users\\dell\\Harmony\\source\\Todo\\entry\\build\\default\\intermediates\\res\\default\\resources\\base\\media\\app_icon.png","type":"file","isSymbolicLink":false,"fileMetaData":{"size":2777,"lastModifiedTime":1734336011208}},{"hashValue":"bb91c5f0bed2c3410805d9615e42a859","name":"background.png","path":"C:\\Users\\dell\\Harmony\\source\\Todo\\entry\\build\\default\\intermediates\\res\\default\\resources\\base\\media\\background.png","type":"file","isSymbolicLink":false,"fileMetaData":{"size":57364,"lastModifiedTime":1734336012155}},{"hashValue":"af351455765061b623e111f1a8d87591","name":"foreground.png","path":"C:\\Users\\dell\\Harmony\\source\\Todo\\entry\\build\\default\\intermediates\\res\\default\\resources\\base\\media\\foreground.png","type":"file","isSymbolicLink":false,"fileMetaData":{"size":12430,"lastModifiedTime":1734336012179}},{"hashValue":"502547eeda21864ac8170cd7850d1d70","name":"layered_image.json","path":"C:\\Users\\dell\\Harmony\\source\\Todo\\entry\\build\\default\\intermediates\\res\\default\\resources\\base\\media\\layered_image.json","type":"file","isSymbolicLink":false,"fileMetaData":{"size":95,"lastModifiedTime":1734526711350}},{"hashValue":"07492a19b1a97de1f1ed179ce76348e5","name":"startIcon.png","path":"C:\\Users\\dell\\Harmony\\source\\Todo\\entry\\build\\default\\intermediates\\res\\default\\resources\\base\\media\\startIcon.png","type":"file","isSymbolicLink":false,"fileMetaData":{"size":20093,"lastModifiedTime":1734336012233}}]},{"hashValue":"9907b8f5c3879467b62b074b46d642b4","name":"profile","path":"C:\\Users\\dell\\Harmony\\source\\Todo\\entry\\build\\default\\intermediates\\res\\default\\resources\\base\\profile","type":"directory","isSymbolicLink":false,"children":[{"hashValue":"173f41df2db9d5c46181454d2e675859","name":"backup_config.json","path":"C:\\Users\\dell\\Harmony\\source\\Todo\\entry\\build\\default\\intermediates\\res\\default\\resources\\base\\profile\\backup_config.json","type":"file","isSymbolicLink":false,"fileMetaData":{"size":36,"lastModifiedTime":1734336012410}},{"hashValue":"f75136053dce9b6d47c882c610abc62e","name":"main_pages.json","path":"C:\\Users\\dell\\Harmony\\source\\Todo\\entry\\build\\default\\intermediates\\res\\default\\resources\\base\\profile\\main_pages.json","type":"file","isSymbolicLink":false,"fileMetaData":{"size":78,"lastModifiedTime":1734475091251}}]}]},{"hashValue":"","name":"rawfile","path":"C:\\Users\\dell\\Harmony\\source\\Todo\\entry\\build\\default\\intermediates\\res\\default\\resources\\rawfile","type":"directory","isSymbolicLink":false,"children":[]}]},"C:\\Users\\dell\\Harmony\\source\\Todo\\entry\\build\\default\\intermediates\\res\\default\\resources.index":{"hashValue":"40c95718ea48821feef076c9ce62350d","name":"resources.index","path":"C:\\Users\\dell\\Harmony\\source\\Todo\\entry\\build\\default\\intermediates\\res\\default\\resources.index","type":"file","isSymbolicLink":false,"fileMetaData":{"size":1415,"lastModifiedTime":1734526711358}},"C:\\Users\\dell\\Harmony\\source\\Todo\\entry\\build\\default\\outputs\\default\\entry-default-unsigned.hap":{"hashValue":"a487d19568c9ac97d01193f107c01b7a","name":"entry-default-unsigned.hap","path":"C:\\Users\\dell\\Harmony\\source\\Todo\\entry\\build\\default\\outputs\\default\\entry-default-unsigned.hap","type":"file","isSymbolicLink":false,"fileMetaData":{"size":252049,"lastModifiedTime":1734570333929}},"C:\\Users\\dell\\Harmony\\source\\Todo\\entry\\build\\default\\outputs\\default\\mapping\\sourceMaps.map":{"hashValue":"fefd7dc4ecc25b61518131b3a7eae388","name":"sourceMaps.map","path":"C:\\Users\\dell\\Harmony\\source\\Todo\\entry\\build\\default\\outputs\\default\\mapping\\sourceMaps.map","type":"file","isSymbolicLink":false,"fileMetaData":{"size":42000,"lastModifiedTime":1734570331833}},"C:\\Users\\dell\\Harmony\\source\\Todo\\build\\cache\\default\\integrated_hsp\\integratedHspCache.json":{"hashValue":"","name":"emptyroot","path":"","type":"unknown","isSymbolicLink":false,"children":[]},"C:\\Users\\dell\\Harmony\\source\\Todo\\entry\\build\\default\\intermediates\\syscap\\default\\rpcid.sc":{"hashValue":"","name":"emptyroot","path":"","type":"unknown","isSymbolicLink":false,"children":[]},"C:\\Users\\dell\\Harmony\\source\\Todo\\entry\\build\\default\\intermediates\\loader_out\\default\\js":{"hashValue":"","name":"emptyroot","path":"","type":"unknown","isSymbolicLink":false,"children":[]},"C:\\Users\\dell\\Harmony\\source\\Todo\\entry\\build\\default\\outputs\\default\\entry-default-signed.hap":{"hashValue":"","name":"emptyroot","path":"","type":"unknown","isSymbolicLink":false,"children":[]}}